tkhtmlview/__init__.py
tkhtmlview/html_parser.py
tkhtmlview/utils.py
tkhtmlview-0.1.3.dist-info/LICENSE
tkhtmlview-0.1.3.dist-info/METADATA
tkhtmlview-0.1.3.dist-info/WHEEL
tkhtmlview-0.1.3.dist-info/RECORD
