Metadata-Version: 2.1
Name: tkhtmlview
Version: 0.1.3
Summary: Display HTML with Tkinter
License: MIT
Author: Palash Bauri
Author-email: palashbauri1@gmail.com
Requires-Python: >=3.7,<4.0
Classifier: License :: OSI Approved :: MIT License
Classifier: Programming Language :: Python :: 3
Classifier: Programming Language :: Python :: 3.7
Classifier: Programming Language :: Python :: 3.8
Classifier: Programming Language :: Python :: 3.9
Classifier: Programming Language :: Python :: 3.10
Classifier: Programming Language :: Python :: 3.11
Requires-Dist: Pillow (>=9.4.0,<10.0.0)
Requires-Dist: requests (>=2.28.2,<3.0.0)
